{
	"info": {
		"_postman_id": "b70b54c1-d658-4fe6-a4f4-1da68990db3c",
		"name": "Take_Home",
		"schema": "https://schema.getpostman.com/json/collection/v2.1.0/collection.json",
		"_exporter_id": "4337002"
	},
	"item": [
		{
			"name": "GET /parts",
			"request": {
				"method": "GET",
				"header": [],
				"url": {
					"raw": "http://localhost:5005/parts",
					"protocol": "http",
					"host": [
						"localhost"
					],
					"port": "5005",
					"path": [
						"parts"
					]
				}
			},
			"response": []
		},
		{
			"name": "GET  /parts/:partId",
			"request": {
				"method": "GET",
				"header": [],
				"url": {
					"raw": "http://localhost:5005/parts/1",
					"protocol": "http",
					"host": [
						"localhost"
					],
					"port": "5005",
					"path": [
						"parts",
						"1"
					]
				}
			},
			"response": []
		},
		{
			"name": "POST /parts",
			"request": {
				"method": "POST",
				"header": [],
				"body": {
					"mode": "raw",
					"raw": "{\n    \"name\": \"Reverse lever!!\",\n    \"sku\": \"DCMM39823DSJW\",\n    \"description\": \"Used for heavy-load computing\",\n    \"weight_ounces\": \"15\",\n    \"is_active\": \"1\"\n}",
					"options": {
						"raw": {
							"language": "json"
						}
					}
				},
				"url": {
					"raw": "http://localhost:5005/parts",
					"protocol": "http",
					"host": [
						"localhost"
					],
					"port": "5005",
					"path": [
						"parts"
					]
				}
			},
			"response": []
		},
		{
			"name": "PATCH /parts/:partId",
			"request": {
				"method": "PATCH",
				"header": [],
				"body": {
					"mode": "raw",
					"raw": "{\n    \"name\": \"Reverse lever!\",\n    \"is_active\": \"1\"\n}",
					"options": {
						"raw": {
							"language": "json"
						}
					}
				},
				"url": {
					"raw": "http://localhost:5005/parts/8",
					"protocol": "http",
					"host": [
						"localhost"
					],
					"port": "5005",
					"path": [
						"parts",
						"8"
					]
				}
			},
			"response": []
		},
		{
			"name": "DELTE /parts/:partId",
			"request": {
				"method": "DELETE",
				"header": [],
				"url": {
					"raw": "http://localhost:5005/parts/7",
					"protocol": "http",
					"host": [
						"localhost"
					],
					"port": "5005",
					"path": [
						"parts",
						"7"
					]
				}
			},
			"response": []
		},
		{
			"name": "GET commonWords",
			"request": {
				"method": "GET",
				"header": [],
				"url": {
					"raw": "http://localhost:5005/parts/commonWords",
					"protocol": "http",
					"host": [
						"localhost"
					],
					"port": "5005",
					"path": [
						"parts",
						"commonWords"
					]
				}
			},
			"response": []
		}
	]
}